pychow/__init__.py
pychow/chow_test.py
pychow-0.1.0.dist-info/LICENSE
pychow-0.1.0.dist-info/METADATA
pychow-0.1.0.dist-info/WHEEL
pychow-0.1.0.dist-info/top_level.txt
pychow-0.1.0.dist-info/RECORD
