Metadata-Version: 2.1
Name: pychow
Version: 0.1.0
Summary: A Python implementation of the Chow Test for structural breaks.
Home-page: https://github.com/amirbabaei97/pychow
Author: Amir Babaei
Author-email: pr.babayee@icloud.com
Classifier: Programming Language :: Python :: 3
Classifier: License :: OSI Approved :: MIT License
Classifier: Operating System :: OS Independent
Requires-Python: >=3.6
License-File: LICENSE
Requires-Dist: numpy
Requires-Dist: pandas
Requires-Dist: statsmodels
Requires-Dist: scipy
